specqp/__init__.py
specqp/datahandler.py
specqp/fitter.py
specqp/fittingmodels.py
specqp/globalfitter.py
specqp/gui.py
specqp/helpers.py
specqp/launcher.py
specqp/plotter.py
specqp/service.py
specqp/assets/specqp_icon.png
specqp-1.1.9.dist-info/LICENSE
specqp-1.1.9.dist-info/METADATA
specqp-1.1.9.dist-info/WHEEL
specqp-1.1.9.dist-info/top_level.txt
specqp-1.1.9.dist-info/RECORD
