Metadata-Version: 2.1
Name: specqp
Version: 1.1.9
Summary: Quick plotting, correcting and fitting of spectroscopic data
Home-page: https://github.com/Shipilin/specqp.git
Author: Mikhail Shipilin
Author-email: mikhail.shipilin@gmail.com
License: MIT
Platform: UNKNOWN
Classifier: Programming Language :: Python :: 3
Classifier: License :: OSI Approved :: MIT License
Classifier: Intended Audience :: Science/Research
Classifier: Natural Language :: English
Classifier: Operating System :: MacOS :: MacOS X
Classifier: Operating System :: Microsoft :: Windows
Classifier: Environment :: MacOS X
Classifier: Development Status :: 5 - Production/Stable
Requires-Dist: numpy
Requires-Dist: scipy
Requires-Dist: pandas
Requires-Dist: matplotlib
Requires-Dist: lmfit
